powerpoint_mcp/__init__.py
powerpoint_mcp/server.py
powerpoint_mcp/tools/__init__.py
powerpoint_mcp/tools/add_slide_with_layout.py
powerpoint_mcp/tools/add_speaker_notes.py
powerpoint_mcp/tools/analyze_template.py
powerpoint_mcp/tools/evaluate.py
powerpoint_mcp/tools/list_templates.py
powerpoint_mcp/tools/manage_slide.py
powerpoint_mcp/tools/populate_placeholder.py
powerpoint_mcp/tools/presentation.py
powerpoint_mcp/tools/skills.py
powerpoint_mcp/tools/snapshot.py
powerpoint_mcp/tools/switch_slide.py
powerpoint_mcp-0.1.1.dist-info/METADATA
powerpoint_mcp-0.1.1.dist-info/WHEEL
powerpoint_mcp-0.1.1.dist-info/entry_points.txt
powerpoint_mcp-0.1.1.dist-info/RECORD
