Metadata-Version: 2.4
Name: powerpoint-mcp
Version: 0.1.1
Summary: Model Context Protocol server for end-to-end PowerPoint presentation creation, analysis, and editing
Author: Ayushmaniar
License: MIT
Keywords: automation,claude,mcp,model-context-protocol,powerpoint,pywin32
Classifier: Operating System :: Microsoft :: Windows
Classifier: Topic :: Office/Business
Requires-Python: >=3.10
Requires-Dist: matplotlib>=3.7.0
Requires-Dist: mcp>=1.14.0
Requires-Dist: numpy>=1.24.0
Requires-Dist: pillow>=10.4.0
Requires-Dist: pywin32>=311
